chaino/__init__.py
chaino/__main__.py
chaino/chaino.py
chaino/hana.py
chaino-0.9.5.dist-info/licenses/LICENSE
chaino-0.9.5.dist-info/METADATA
chaino-0.9.5.dist-info/WHEEL
chaino-0.9.5.dist-info/top_level.txt
chaino-0.9.5.dist-info/RECORD
