Metadata-Version: 2.4
Name: chaino
Version: 0.9.5
Summary: python lib for Arduino Chaino device
Author-email: Jang-Hyun Park <salesiopark@gmail.com>
License: MIT License
Project-URL: Homepage, https://github.com/salesiopark/pychaino
Project-URL: Issues, https://github.com/salesiopark/pychaino/issues
Keywords: arduino,serial,i2c
Classifier: Programming Language :: Python :: 3
Classifier: License :: OSI Approved :: MIT License
Classifier: Operating System :: OS Independent
Requires-Python: >=3.8
License-File: LICENSE
Dynamic: license-file
